sport/__init__.py
sport/abstract.py
sport/api.py
sport/interface.py
sport/report_service.py
sport/search_center.py
sport/tool.py
digital_sport-0.2.2.dist-info/METADATA
digital_sport-0.2.2.dist-info/WHEEL
digital_sport-0.2.2.dist-info/top_level.txt
digital_sport-0.2.2.dist-info/RECORD
