Metadata-Version: 2.1
Name: digital-sport
Version: 0.2.2
Summary: Sport Api - structured data.
Home-page: https://github.com/repen/digital-sport
Author: Andrey Plugin
Author-email: 9keepa@gmail.com
License: MIT
Platform: UNKNOWN
Requires-Python: >=3.6
Requires-Dist: requests
